pipfile_upgrade/__init__.py
pipfile_upgrade/__main__.py
pipfile_upgrade/argument_parser.py
pipfile_upgrade/dataclasses.py
pipfile_upgrade/errors.py
pipfile_upgrade/pipfile.py
pipfile_upgrade/tomlfile.py
pipfile_upgrade-0.0.2.dist-info/LICENSE.txt
pipfile_upgrade-0.0.2.dist-info/METADATA
pipfile_upgrade-0.0.2.dist-info/WHEEL
pipfile_upgrade-0.0.2.dist-info/entry_points.txt
pipfile_upgrade-0.0.2.dist-info/top_level.txt
pipfile_upgrade-0.0.2.dist-info/RECORD
